setup.py
trackingshell/__init__.py
trackingshell/decorators.py
trackingshell/tests.py
trackingshell.egg-info/PKG-INFO
trackingshell.egg-info/SOURCES.txt
trackingshell.egg-info/dependency_links.txt
trackingshell.egg-info/entry_points.txt
trackingshell.egg-info/not-zip-safe
trackingshell.egg-info/top_level.txt