Metadata-Version: 1.0
Name: trackingshell
Version: 1.0.1
Summary: You can track the target execution of a makefile with this tool easily.
Home-page: http://6wunderkinder.com
Author: Bence Faludi, Torsten Becker
Author-email: befaludi@microsoft.com
License: MIT
Platform: UNKNOWN
